onepagecrm/__init__.py
onepagecrm/onepagecrm.py
onepagecrm-0.2.0.dist-info/METADATA
onepagecrm-0.2.0.dist-info/WHEEL
onepagecrm-0.2.0.dist-info/top_level.txt
onepagecrm-0.2.0.dist-info/RECORD
