Metadata-Version: 2.1
Name: onepagecrm
Version: 0.2.0
Summary: Connect and interface with the OnePageCRM REST API
Home-page: https://github.com/onepagecrm/python-client
Author: Ruairi Fahy
Author-email: devteam@onepagecrm.com
License: MIT
Platform: UNKNOWN
Requires-Dist: requests
